{
  "architecture": {
    "title": "Architecture",
    "slug": "architecture",
    "anchor": "architecture"
  },
  "catalog-structure": {
    "title": "Designing of catalog structure",
    "slug": "catalog-structure",
    "anchor": "designing-of-catalog-structure"
  },
  "modules": {
    "title": "<span style=\"color: red\">**Modules**</span>",
    "slug": "home"
  },
  "artisan-commands": {
    "title": "Artisan commands",
    "slug": "home",
    "anchor": "artisan-commands"
  },
  "import": {
    "title": "Import",
    "slug": "import-from-xml/home",
    "anchor": "import-from-xml"
  },
  "plugins": {
    "title": "Plugins",
    "slug": "home"
  },
  "changelog": {
    "title": "Changelog",
    "slug": "changelog"
  }
}